myapp/__init__.py
myapp/cli.py
myapp_secure_cli-0.1.0.dist-info/licenses/LICENSE
myapp_secure_cli-0.1.0.dist-info/METADATA
myapp_secure_cli-0.1.0.dist-info/WHEEL
myapp_secure_cli-0.1.0.dist-info/entry_points.txt
myapp_secure_cli-0.1.0.dist-info/top_level.txt
myapp_secure_cli-0.1.0.dist-info/RECORD
