Metadata-Version: 2.4
Name: myapp-secure-cli
Version: 0.1.0
Summary: myapp — minimal secure CLI demo (test only)
Author-email: Your Name <you@example.com>
License-Expression: MIT
Project-URL: Homepage, https://github.com/yourusername/myapp
Project-URL: Repository, https://github.com/yourusername/myapp
Project-URL: Issues, https://github.com/yourusername/myapp/issues
Keywords: cli,security,encryption,mongodb,credentials
Classifier: Development Status :: 3 - Alpha
Classifier: Intended Audience :: Developers
Classifier: Programming Language :: Python :: 3
Classifier: Programming Language :: Python :: 3.9
Classifier: Programming Language :: Python :: 3.10
Classifier: Programming Language :: Python :: 3.11
Classifier: Programming Language :: Python :: 3.12
Requires-Python: >=3.9
License-File: LICENSE
Requires-Dist: typer[all]>=0.9.0
Requires-Dist: pymongo>=4.0.0
Requires-Dist: cryptography>=40.0.0
Requires-Dist: keyring>=24.0.0
Dynamic: license-file
